debug_toolbar/__init__.py
debug_toolbar/core/__init__.py
debug_toolbar/core/config.py
debug_toolbar/core/context.py
debug_toolbar/core/panel.py
debug_toolbar/core/panels/__init__.py
debug_toolbar/core/panels/alerts.py
debug_toolbar/core/panels/async_profiler/__init__.py
debug_toolbar/core/panels/async_profiler/base.py
debug_toolbar/core/panels/async_profiler/detector.py
debug_toolbar/core/panels/async_profiler/models.py
debug_toolbar/core/panels/async_profiler/panel.py
debug_toolbar/core/panels/async_profiler/taskfactory.py
debug_toolbar/core/panels/async_profiler/timeline.py
debug_toolbar/core/panels/cache.py
debug_toolbar/core/panels/flamegraph.py
debug_toolbar/core/panels/headers.py
debug_toolbar/core/panels/logging.py
debug_toolbar/core/panels/memory/__init__.py
debug_toolbar/core/panels/memory/base.py
debug_toolbar/core/panels/memory/memray.py
debug_toolbar/core/panels/memory/panel.py
debug_toolbar/core/panels/memory/tracemalloc.py
debug_toolbar/core/panels/profiling.py
debug_toolbar/core/panels/request.py
debug_toolbar/core/panels/response.py
debug_toolbar/core/panels/settings.py
debug_toolbar/core/panels/templates.py
debug_toolbar/core/panels/timer.py
debug_toolbar/core/panels/versions.py
debug_toolbar/core/panels/websocket.py
debug_toolbar/core/storage.py
debug_toolbar/core/toolbar.py
debug_toolbar/extras/__init__.py
debug_toolbar/extras/advanced_alchemy/__init__.py
debug_toolbar/extras/advanced_alchemy/panel.py
debug_toolbar/extras/strawberry/__init__.py
debug_toolbar/extras/strawberry/analyzers.py
debug_toolbar/extras/strawberry/extension.py
debug_toolbar/extras/strawberry/models.py
debug_toolbar/extras/strawberry/panel.py
debug_toolbar/extras/strawberry/utils.py
debug_toolbar/fastapi/__init__.py
debug_toolbar/fastapi/config.py
debug_toolbar/fastapi/middleware.py
debug_toolbar/fastapi/panels/__init__.py
debug_toolbar/fastapi/panels/dependencies.py
debug_toolbar/fastapi/setup.py
debug_toolbar/litestar/__init__.py
debug_toolbar/litestar/config.py
litestar_debug_toolbar-0.4.2.dist-info/WHEEL
litestar_debug_toolbar-0.4.2.dist-info/METADATA
litestar_debug_toolbar-0.4.2.dist-info/RECORD
