Metadata-Version: 2.3
Name: litestar-debug-toolbar
Version: 0.4.2
Summary: Async-native debug toolbar for Python ASGI frameworks with optional Litestar integration
Keywords: async,asgi,debug,toolbar,profiling,litestar,fastapi,starlette
Author: Jacob Coffee
Author-email: Jacob Coffee <jacob@z7x.org>
License: MIT
Classifier: Development Status :: 3 - Alpha
Classifier: Environment :: Web Environment
Classifier: Framework :: AsyncIO
Classifier: Intended Audience :: Developers
Classifier: License :: OSI Approved :: MIT License
Classifier: Operating System :: OS Independent
Classifier: Programming Language :: Python
Classifier: Programming Language :: Python :: 3
Classifier: Programming Language :: Python :: 3.10
Classifier: Programming Language :: Python :: 3.11
Classifier: Programming Language :: Python :: 3.12
Classifier: Programming Language :: Python :: 3.13
Classifier: Programming Language :: Python :: 3 :: Only
Classifier: Topic :: Internet :: WWW/HTTP
Classifier: Topic :: Software Development :: Debuggers
Classifier: Topic :: Software Development :: Libraries :: Python Modules
Classifier: Typing :: Typed
Requires-Dist: jinja2>=3.1.0
Requires-Dist: markupsafe>=2.1.0
Requires-Dist: advanced-alchemy>=0.10.0 ; extra == 'advanced-alchemy'
Requires-Dist: aiosqlite>=0.19.0 ; extra == 'advanced-alchemy'
Requires-Dist: sqlalchemy>=2.0.0 ; extra == 'advanced-alchemy'
Requires-Dist: debug-toolbar[litestar,starlette,fastapi,advanced-alchemy,strawberry,mcp] ; extra == 'all'
Requires-Dist: fastapi>=0.100.0 ; extra == 'fastapi'
Requires-Dist: litestar>=2.0.0 ; extra == 'litestar'
Requires-Dist: mcp>=1.0.0 ; extra == 'mcp'
Requires-Dist: starlette>=0.27.0 ; extra == 'starlette'
Requires-Dist: strawberry-graphql>=0.240.0 ; extra == 'strawberry'
Requires-Python: >=3.10, <3.14
Project-URL: Changelog, https://github.com/JacobCoffee/debug-toolbar/releases/
Project-URL: Discord, https://discord.gg/litestar-919193495116337154
Project-URL: Documentation, https://jacobcoffee.github.io/debug-toolbar
Project-URL: Homepage, https://github.com/JacobCoffee/debug-toolbar
Project-URL: Issue Tracker, https://github.com/JacobCoffee/debug-toolbar/issues
Project-URL: Repository, https://github.com/JacobCoffee/debug-toolbar
Provides-Extra: advanced-alchemy
Provides-Extra: all
Provides-Extra: fastapi
Provides-Extra: litestar
Provides-Extra: mcp
Provides-Extra: starlette
Provides-Extra: strawberry
